xdeeprank/__init__.py
xdeeprank/models/__init__.py
xdeeprank/models/deepfm.py
xdeeprank-0.0.1.dist-info/LICENSE
xdeeprank-0.0.1.dist-info/METADATA
xdeeprank-0.0.1.dist-info/WHEEL
xdeeprank-0.0.1.dist-info/top_level.txt
xdeeprank-0.0.1.dist-info/RECORD
