Metadata-Version: 2.1
Name: xdeeprank
Version: 0.0.1
Summary: An eXtensible package of deep learning based ranking models for large-scale industrial recommender system with tensorflow
Home-page: https://github.com/imsheridan/xDeepRank
Author: deepdeliver
Author-email: xiaoyudong0512@gmail.com
License: UNKNOWN
Keywords: ctr,click through rate,recommender system,industrial,deep learning,tensorflow
Platform: UNKNOWN
Classifier: Programming Language :: Python :: 3
Classifier: License :: OSI Approved :: Apache Software License
Classifier: Operating System :: OS Independent
Requires-Python: >=3.6
